{
  "grace_hours": 24,
  "devices": [
    {
      "hwid": "87e35eeed6e19fb3dfcbd4c82e329cd41a8ecc158564baadec007cd621a2e72",
      "enabled": true,
      "expire_at": "2026-08-08T09:09:01Z",
      "perm": {
        "menu3": true,
        "menu4": true
      },
      "success_limit": 10,
      "success_used": 0
    },
    {
      "hwid": "dcc75442a7688bc4791087b1faf7f8cc30c363f2ee5729018176e30774b3704e",
      "enabled": true,
      "expire_at": "2026-08-08T10:19:35Z",
      "perm": {
        "menu3": true,
        "menu4": true
      },
      "success_limit": 10,
      "success_used": 0
    }
  ]
}